discogs_wrapper/__init__.py
discogs_wrapper/dv.py
discogs_wrapper_python-1.0.1.dist-info/METADATA
discogs_wrapper_python-1.0.1.dist-info/WHEEL
discogs_wrapper_python-1.0.1.dist-info/top_level.txt
discogs_wrapper_python-1.0.1.dist-info/RECORD
