Metadata-Version: 2.1
Name: discogs-wrapper-python
Version: 1.0.1
Summary: This is a python API wrapper for the discogs API.
Home-page: UNKNOWN
Author: Gargee Bhase
Author-email: gbhase2@gmail.com
License: MIT
Platform: UNKNOWN
